[
  {
    "id": 1,
    "number": 1,
    "key":  "bill_all_pending",
    "display": "\uD83D\uDD79 Данные от панели управления"
  },
  {
    "id": 2,
    "number": 99999,
    "key":  "bill_all_pending_bill_all_bill_all_pendingbill_all_pendingbill_all_pending_ bill_all_pending_bill_all_pending_bill",
    "display": "⌛\uFE0F  Ветер гонит листву. Старых лампочек тусклый накал в этих грустных краях, чей эпиграф — победа зеркал, при содействии луж порождает эффект изобилья. Даже воры крадут апельсин, амальгаму скребя. Впрочем, чувство, с которым глядишь на себя, — это чувство забыл я. В этих грустных краях все рассчитано на зим"
  },
  {
    "id": 3,
    "number": 1,
    "key":  "bill_all_pending",
    "display": "\uD83D\uDD79 Данные от панели управления"
  }
]